DataServices/__init__.py
DataServices/config/logging_config.py
DataServices/config/spciq-api-dataservices-application.properties
DataServices/constants/sdk_constants.py
DataServices/model/sdk_data_input.py
DataServices/model/sdk_data_input_base.py
DataServices/model/sdk_data_request.py
DataServices/model/sdk_proxy.py
DataServices/services/sdk_data_services.py
DataServices/services/helper/data_transform_util.py
DataServices/services/helper/request_director.py
DataServices/services/impl/sdk_data_services_impl.py
DataServices/services/support/rest_gateway_support.py
DataServices/util/LogFileHandler.py
DataServices/util/default_properties.py
DataServices/util/property_utils.py
dataservicestestdistribution-1.0.4.dist-info/METADATA
dataservicestestdistribution-1.0.4.dist-info/WHEEL
dataservicestestdistribution-1.0.4.dist-info/top_level.txt
dataservicestestdistribution-1.0.4.dist-info/RECORD
