Metadata-Version: 2.1
Name: dataservicestestdistribution
Version: 1.0.4
Summary: Module for dataservices pkg distribution test
Author-email: sp <sp@email.com>
Classifier: Programming Language :: Python :: 3
Classifier: License :: OSI Approved :: MIT License
Classifier: Operating System :: OS Independent
Requires-Python: >=3.12
Requires-Dist: requests
Requires-Dist: pandas
